Compiled from "Recipe037Test.java"
class com.example.java8.chapter02.Recipe037Test$1 implements java.util.Comparator<java.lang.String> {
  final com.example.java8.chapter02.Recipe037Test this$0;

  com.example.java8.chapter02.Recipe037Test$1(com.example.java8.chapter02.Recipe037Test);
    Code:
       0: aload_0       
       1: aload_1       
       2: putfield      #1                  // Field this$0:Lcom/example/java8/chapter02/Recipe037Test;
       5: aload_0       
       6: invokespecial #2                  // Method java/lang/Object."<init>":()V
       9: return        

  public int compare(java.lang.String, java.lang.String);
    Code:
       0: aload_1       
       1: invokevirtual #3                  // Method java/lang/String.length:()I
       4: aload_2       
       5: invokevirtual #3                  // Method java/lang/String.length:()I
       8: isub          
       9: ireturn       

  public int compare(java.lang.Object, java.lang.Object);
    Code:
       0: aload_0       
       1: aload_1       
       2: checkcast     #4                  // class java/lang/String
       5: aload_2       
       6: checkcast     #4                  // class java/lang/String
       9: invokevirtual #5                  // Method compare:(Ljava/lang/String;Ljava/lang/String;)I
      12: ireturn       
}
